{
  "commit": "6e381e0441fd97d403b0133d4628d700d929b345",
  "generated": "2024-04-22T13:19:40.484Z",
  "metadata": [
    {
      "__outstatic": {
        "commit": "3840a7db257e3229399106ce34fc0712e8ce455a",
        "hash": "337057040",
        "path": "outstatic/content/pages/home.md"
      },
      "author": {
        "name": "Rickard Sandgren",
        "picture": "https://avatars.githubusercontent.com/u/2293029?v=4"
      },
      "collection": "pages",
      "coverImage": "",
      "description": "",
      "publishedAt": "2024-04-22T10:26:12.078Z",
      "slug": "home",
      "status": "published",
      "title": "Home"
    },
    {
      "__outstatic": {
        "commit": "a3791d499b941ed0cc6ec3e67809325283d8728a",
        "hash": "2464316235",
        "path": "outstatic/content/pages/about.md"
      },
      "author": {
        "name": "Rickard Sandgren",
        "picture": "https://avatars.githubusercontent.com/u/2293029?v=4"
      },
      "collection": "pages",
      "coverImage": "",
      "description": "",
      "publishedAt": "2024-04-19T13:51:27.097Z",
      "slug": "about",
      "status": "published",
      "title": "About"
    },
    {
      "__outstatic": {
        "commit": "267e99b77ea420785e890f897912ac36962e103e",
        "hash": "3283795178",
        "path": "outstatic/content/cakes/blizzfull-yum.md"
      },
      "author": {
        "name": "Rickard Sandgren",
        "picture": "https://avatars.githubusercontent.com/u/2293029?v=4"
      },
      "collection": "cakes",
      "coverImage": "",
      "description": "",
      "price": "499",
      "publishedAt": "2024-04-22T12:12:56.403Z",
      "slug": "blizzfull-yum",
      "status": "published",
      "title": "Blizzfull Yum",
      "typeOfCake": [
        {
          "label": "wedding cake",
          "value": "weddingCake"
        }
      ]
    },
    {
      "__outstatic": {
        "commit": "6e3839fe48037db4b2d6928c415fe324d7a96402",
        "hash": "2434170397",
        "path": "outstatic/content/pages/contact.md"
      },
      "author": {
        "name": "Rickard Sandgren",
        "picture": "https://avatars.githubusercontent.com/u/2293029?v=4"
      },
      "collection": "pages",
      "coverImage": "",
      "description": "",
      "publishedAt": "2024-04-22T11:11:40.729Z",
      "slug": "contact",
      "status": "published",
      "title": "Contact"
    },
    {
      "__outstatic": {
        "commit": "0c22147011c80fcfe3a0c56965476b0c9ad28d53",
        "hash": "2457502398",
        "path": "outstatic/content/cakes/fluffy-amazing.md"
      },
      "author": {
        "name": "Rickard Sandgren",
        "picture": "https://avatars.githubusercontent.com/u/2293029?v=4"
      },
      "collection": "cakes",
      "coverImage": "/images/american-buttercream_hero-k4Nj.webp",
      "description": "",
      "price": "79",
      "publishedAt": "2024-04-22T12:11:45.031Z",
      "slug": "fluffy-amazing",
      "status": "published",
      "title": "Fluffy Amazing",
      "typeOfCake": [
        {
          "label": "cupcake",
          "value": "cupcake"
        }
      ]
    },
    {
      "__outstatic": {
        "commit": "31d64c107709c38e1399d389446ff4b18a24aa18",
        "hash": "2881270956",
        "path": "outstatic/content/cakes/chokolate-dream.md"
      },
      "author": {
        "name": "Rickard Sandgren",
        "picture": "https://avatars.githubusercontent.com/u/2293029?v=4"
      },
      "collection": "cakes",
      "coverImage": "/images/chocolate-cupcakes.webp",
      "description": "",
      "price": "79",
      "publishedAt": "2024-04-22T13:21:23.089Z",
      "slug": "chokolate-dream",
      "status": "published",
      "title": "Chokolate Dream",
      "typeOfCake": [
        {
          "label": "cupcake",
          "value": "cupcake"
        }
      ]
    },
    {
      "__outstatic": {
        "commit": "690fd0eace141495bf03bef91d17c01a3a62ed70",
        "hash": "3276635315",
        "path": "outstatic/content/cakes/matcha-grab-bite.md"
      },
      "author": {
        "name": "Rickard Sandgren",
        "picture": "https://avatars.githubusercontent.com/u/2293029?v=4"
      },
      "collection": "cakes",
      "coverImage": "/images/Matcha-Cupcakes.jpg",
      "description": "",
      "price": "79",
      "publishedAt": "2024-04-22T13:27:14.349Z",
      "slug": "matcha-grab-bite",
      "status": "published",
      "title": "Matcha Grab-bite",
      "typeOfCake": [
        {
          "label": "cupcake",
          "value": "cupcake"
        }
      ]
    },
    {
      "__outstatic": {
        "commit": "4f0db6cb716d4c3dd1878020ee1589bcca6c264c",
        "hash": "1948332055",
        "path": "outstatic/content/cakes/mister-moisty.md"
      },
      "author": {
        "name": "Rickard Sandgren",
        "picture": "https://avatars.githubusercontent.com/u/2293029?v=4"
      },
      "collection": "cakes",
      "coverImage": "/images/moistchokolate.webp",
      "description": "",
      "price": "29",
      "publishedAt": "2024-04-22T13:28:51.370Z",
      "slug": "mister-moisty",
      "status": "published",
      "title": "Mister moisty",
      "typeOfCake": [
        {
          "label": "cupcake",
          "value": "cupcake"
        }
      ]
    },
    {
      "__outstatic": {
        "commit": "93db3f3b4079a129f4764a5ba0aae384505369f1",
        "hash": "4007706902",
        "path": "outstatic/content/cakes/creamy-orange.md"
      },
      "author": {
        "name": "Rickard Sandgren",
        "picture": "https://avatars.githubusercontent.com/u/2293029?v=4"
      },
      "collection": "cakes",
      "coverImage": "/images/OrangeCreamsicleCupcakes_featured.jpg",
      "description": "",
      "price": "49",
      "publishedAt": "2024-04-22T13:29:56.114Z",
      "slug": "creamy-orange",
      "status": "published",
      "title": "Creamy Orange",
      "typeOfCake": [
        {
          "label": "cupcake",
          "value": "cupcake"
        }
      ]
    },
    {
      "__outstatic": {
        "commit": "6e381e0441fd97d403b0133d4628d700d929b345",
        "hash": "445027641",
        "path": "outstatic/content/cakes/heyhey-oreo.md"
      },
      "author": {
        "name": "Rickard Sandgren",
        "picture": "https://avatars.githubusercontent.com/u/2293029?v=4"
      },
      "collection": "cakes",
      "coverImage": "/images/Oreo-Cupcakes-Square-1.jpg",
      "description": "",
      "price": "35",
      "publishedAt": "2024-04-22T13:31:03.156Z",
      "slug": "heyhey-oreo",
      "status": "published",
      "title": "Heyhey Oreo!",
      "typeOfCake": [
        {
          "label": "cupcake",
          "value": "cupcake"
        }
      ]
    }
  ]
}